setup.py
butler/__init__.py
butler/__version__.py
butler/butler.py
butler/butler_function.py
butler/client.py
butler/server.py
http_butler.egg-info/PKG-INFO
http_butler.egg-info/SOURCES.txt
http_butler.egg-info/dependency_links.txt
http_butler.egg-info/requires.txt
http_butler.egg-info/top_level.txt