Metadata-Version: 1.1
Name: http-butler
Version: 0.3.3
Summary: Light flask server
Home-page: https://github.com/eplaut/python-butler
Author: Eli Plaut
Author-email: eplaut@gmail.com
License: BSD
Platform: UNKNOWN
Classifier: Programming Language :: Python :: 2.7
Classifier: Programming Language :: Python :: 3.3
Classifier: Programming Language :: Python :: 3.4
Classifier: Programming Language :: Python :: 3.5
